programmingForData/BudgetHandler.py
programmingForData/CategoricalEncoder.py
programmingForData/DataFilter.py
programmingForData/DataTypeConverter.py
programmingForData/DateTimeHandler.py
programmingForData/MissingValueHandler.py
programmingForData/OutlierHandler.py
programmingForData/Scaler.py
programmingForData/Test.py
programmingForData/Visualizer.py
programmingForData/__init__.py
programmingForData-0.2.0.dist-info/LICENSE
programmingForData-0.2.0.dist-info/METADATA
programmingForData-0.2.0.dist-info/WHEEL
programmingForData-0.2.0.dist-info/top_level.txt
programmingForData-0.2.0.dist-info/RECORD
