Metadata-Version: 2.1
Name: programmingForData
Version: 0.2.0
Summary: A comprehensive library for data preprocessing tasks
Home-page: https://github.com/beyzasevigen/programmingForData
Author: Beyza Nur Sevigen, Meryem Kilic
Author-email: beyzanur.sevigen@stu.fsm.edu.tr, meryem.kilic@stu.fsm.edu.tr
Classifier: Programming Language :: Python :: 3
Classifier: License :: OSI Approved :: MIT License
Classifier: Operating System :: OS Independent
Requires-Python: >=3.6
License-File: LICENSE
Requires-Dist: pandas (>=1.1.5)
Requires-Dist: numpy (>=1.19.5)
Requires-Dist: scikit-learn (>=0.24.2)
Requires-Dist: matplotlib (>=3.3.4)
Requires-Dist: seaborn (>=0.11.1)
Requires-Dist: nltk (>=3.6.1)
Requires-Dist: scipy (>=1.6.2)
